invenio_users_resources/__init__.py
invenio_users_resources/config.py
invenio_users_resources/entity_resolvers.py
invenio_users_resources/ext.py
invenio_users_resources/forms.py
invenio_users_resources/models.py
invenio_users_resources/permissions.py
invenio_users_resources/proxies.py
invenio_users_resources/views.py
invenio_users_resources/notifications/__init__.py
invenio_users_resources/notifications/filters.py
invenio_users_resources/notifications/generators.py
invenio_users_resources/records/__init__.py
invenio_users_resources/records/api.py
invenio_users_resources/records/hooks.py
invenio_users_resources/records/models.py
invenio_users_resources/records/dumpers/__init__.py
invenio_users_resources/records/dumpers/email.py
invenio_users_resources/records/mappings/__init__.py
invenio_users_resources/records/mappings/os-v1/__init__.py
invenio_users_resources/records/mappings/os-v1/domains/domain-v1.0.0.json
invenio_users_resources/records/mappings/os-v1/groups/group-v1.0.0.json
invenio_users_resources/records/mappings/os-v1/groups/group-v2.0.0.json
invenio_users_resources/records/mappings/os-v1/users/user-v1.0.0.json
invenio_users_resources/records/mappings/os-v1/users/user-v2.0.0.json
invenio_users_resources/records/mappings/os-v1/users/user-v3.0.0.json
invenio_users_resources/records/mappings/os-v2/__init__.py
invenio_users_resources/records/mappings/os-v2/domains/domain-v1.0.0.json
invenio_users_resources/records/mappings/os-v2/groups/group-v1.0.0.json
invenio_users_resources/records/mappings/os-v2/groups/group-v2.0.0.json
invenio_users_resources/records/mappings/os-v2/users/user-v1.0.0.json
invenio_users_resources/records/mappings/os-v2/users/user-v2.0.0.json
invenio_users_resources/records/mappings/os-v2/users/user-v3.0.0.json
invenio_users_resources/records/mappings/v7/__init__.py
invenio_users_resources/records/mappings/v7/domains/domain-v1.0.0.json
invenio_users_resources/records/mappings/v7/groups/group-v1.0.0.json
invenio_users_resources-10.0.0.dist-info/licenses/AUTHORS.rst
invenio_users_resources-10.0.0.dist-info/licenses/LICENSE
invenio_users_resources-10.0.0.dist-info/METADATA
invenio_users_resources-10.0.0.dist-info/WHEEL
invenio_users_resources-10.0.0.dist-info/entry_points.txt
invenio_users_resources-10.0.0.dist-info/top_level.txt
invenio_users_resources-10.0.0.dist-info/RECORD
